vibraniumdome_sdk/__init__.py
vibraniumdome_sdk-0.6.0.dist-info/LICENSE
vibraniumdome_sdk-0.6.0.dist-info/METADATA
vibraniumdome_sdk-0.6.0.dist-info/WHEEL
vibraniumdome_sdk-0.6.0.dist-info/RECORD
