Metadata-Version: 2.1
Name: vibraniumdome-sdk
Version: 0.6.0
Summary: vibraniumdome-sdk
Author: Uri Shamay
Author-email: cmpxchg16@gmail.com
Requires-Python: >=3.9,<4.0
Classifier: Programming Language :: Python :: 3
Classifier: Programming Language :: Python :: 3.9
Classifier: Programming Language :: Python :: 3.10
Classifier: Programming Language :: Python :: 3.11
Classifier: Programming Language :: Python :: 3.12
Requires-Dist: traceloop-sdk (>=0.15.4,<0.16.0)
